ctapi/__init__.py
ctapi/ctapi.py
python_ctapi-0.3.0.dist-info/DESCRIPTION.rst
python_ctapi-0.3.0.dist-info/METADATA
python_ctapi-0.3.0.dist-info/metadata.json
python_ctapi-0.3.0.dist-info/RECORD
python_ctapi-0.3.0.dist-info/top_level.txt
python_ctapi-0.3.0.dist-info/WHEEL
