Metadata-Version: 2.0
Name: python-ctapi
Version: 0.3.0
Summary: Python Interface for CoinTracking.info API
Home-page: https://github.com/tbl42/python-ctapi
Author: tbl42
Author-email: cyberworker@posteo.de
License: MIT
Keywords: cointracking info btc api
Platform: UNKNOWN
Classifier: Programming Language :: Python
Classifier: Programming Language :: Python :: 2
Classifier: Programming Language :: Python :: 2.7
Classifier: Programming Language :: Python :: 3
Classifier: Programming Language :: Python :: 3.4
Classifier: Programming Language :: Python :: 3.5
Classifier: Programming Language :: Python :: 3.6
Classifier: Operating System :: OS Independent
Classifier: License :: OSI Approved :: MIT License
Classifier: Intended Audience :: Developers
Classifier: Topic :: Office/Business :: Financial
Requires-Dist: requests (==2.18.4)
Requires-Dist: future (==0.16.0)
Requires-Dist: PyYAML (==3.11)
